jcryptor/__init__.py
jcryptor/main.py
JCryptor-0.1.70.dist-info/LICENCE
JCryptor-0.1.70.dist-info/METADATA
JCryptor-0.1.70.dist-info/WHEEL
JCryptor-0.1.70.dist-info/top_level.txt
JCryptor-0.1.70.dist-info/RECORD
