Metadata-Version: 2.1
Name: JCryptor
Version: 0.1.70
Summary: JCryptor: The Encryptor and Decryptor Module
Home-page: https://github.com/ScripNewbie/JCryptor
Author: CodeBoard
Author-email: jdmaster888@gmail.com
License: UNKNOWN
Keywords: encrypt,decrypt,jcryptor
Platform: UNKNOWN
Classifier: Programming Language :: Python :: 3
Classifier: License :: OSI Approved :: MIT License
Classifier: Operating System :: OS Independent
License-File: LICENCE
